{
  "1": [
    {
      "pname": "Reachability",
      "endLocation": 1,
      "flowID": 1,
      "startLocation": 3,
      "lastSeen": 207,
      "largestGap": 196,
      "gapF": 196,
      "gapS": 0,
      "received_times": [
        "17:23:19.380",
        "17:23:19.383",
        "17:23:19.419",
        "17:23:19.502",
        "17:23:19.504",
        "17:23:19.541",
        "17:23:19.623",
        "17:23:19.627",
        "17:23:19.663",
        "17:23:19.727",
        "17:23:19.730",
        "17:23:19.766",
        "17:23:19.840",
        "17:23:19.880",
        "17:23:19.966",
        "17:23:20.005",
        "17:23:20.089",
        "17:23:20.131",
        "17:23:31.352",
        "17:23:31.355",
        "17:23:31.359",
        "17:23:31.363",
        "17:23:31.366",
        "17:23:31.371",
        "17:23:31.374",
        "17:23:31.379",
        "17:23:31.384",
        "17:23:31.389",
        "17:23:31.391",
        "17:23:31.428",
        "17:23:31.462",
        "17:23:31.497",
        "17:23:31.529",
        "17:23:31.561",
        "17:23:31.593",
        "17:23:31.624",
        "17:23:31.659",
        "17:23:31.694"
      ],
      "processing_times": [
        "17:23:19.380",
        "17:23:19.383",
        "17:23:19.419",
        "17:23:19.502",
        "17:23:19.504",
        "17:23:19.541",
        "17:23:19.623",
        "17:23:19.627",
        "17:23:19.663",
        "17:23:19.727",
        "17:23:19.730",
        "17:23:19.766",
        "17:23:19.840",
        "17:23:19.880",
        "17:23:19.966",
        "17:23:20.005",
        "17:23:20.089",
        "17:23:20.131",
        "17:23:31.352",
        "17:23:31.355",
        "17:23:31.359",
        "17:23:31.363",
        "17:23:31.366",
        "17:23:31.371",
        "17:23:31.374",
        "17:23:31.379",
        "17:23:31.384",
        "17:23:31.389",
        "17:23:31.391",
        "17:23:31.428",
        "17:23:31.462",
        "17:23:31.497",
        "17:23:31.529",
        "17:23:31.561",
        "17:23:31.593",
        "17:23:31.624",
        "17:23:31.659",
        "17:23:31.694"
      ]
    },
    {
      "pname": "Waypoint",
      "endLocation": 1,
      "flowID": 1,
      "startLocation": 3,
      "expectedWaypoints": [
        "s3"
      ],
      "unexpectedWaypoints": [],
      "errorFound": 0,
      "received_times": [
        "17:23:19.380",
        "17:23:19.502",
        "17:23:19.623",
        "17:23:19.727",
        "17:23:19.840",
        "17:23:19.966",
        "17:23:20.089"
      ],
      "processing_times": [
        "17:23:19.380",
        "17:23:19.502",
        "17:23:19.623",
        "17:23:19.727",
        "17:23:19.840",
        "17:23:19.966",
        "17:23:20.089"
      ]
    },
    {
      "pname": "Waypoint",
      "endLocation": 1,
      "flowID": 2,
      "startLocation": 6,
      "expectedWaypoints": [
        "s3"
      ],
      "unexpectedWaypoints": [],
      "errorFound": 0,
      "received_times": [
        "17:23:19.419",
        "17:23:19.541",
        "17:23:19.663",
        "17:23:19.766",
        "17:23:19.880",
        "17:23:20.005",
        "17:23:20.131"
      ],
      "processing_times": [
        "17:23:19.419",
        "17:23:19.541",
        "17:23:19.663",
        "17:23:19.766",
        "17:23:19.880",
        "17:23:20.005",
        "17:23:20.131"
      ]
    }
  ],
  "6": [
    {
      "pname": "Reachability",
      "endLocation": 6,
      "flowID": 2,
      "startLocation": 5,
      "lastSeen": 191,
      "largestGap": 180,
      "gapF": 180,
      "gapS": 0,
      "received_times": [
        "17:23:19.399",
        "17:23:19.399",
        "17:23:19.423",
        "17:23:19.520",
        "17:23:19.521",
        "17:23:19.545",
        "17:23:19.643",
        "17:23:19.643",
        "17:23:19.667",
        "17:23:19.746",
        "17:23:19.747",
        "17:23:19.770",
        "17:23:19.860",
        "17:23:19.860",
        "17:23:19.985",
        "17:23:19.985",
        "17:23:20.108",
        "17:23:20.108",
        "17:23:31.365",
        "17:23:31.403",
        "17:23:31.440",
        "17:23:31.474",
        "17:23:31.509",
        "17:23:31.530",
        "17:23:31.533",
        "17:23:31.536",
        "17:23:31.539",
        "17:23:31.541",
        "17:23:31.545",
        "17:23:31.547",
        "17:23:31.550",
        "17:23:31.554",
        "17:23:31.558",
        "17:23:31.578",
        "17:23:31.609",
        "17:23:31.643",
        "17:23:31.680",
        "17:23:31.715"
      ],
      "processing_times": [
        "17:23:19.399",
        "17:23:19.399",
        "17:23:19.423",
        "17:23:19.520",
        "17:23:19.521",
        "17:23:19.545",
        "17:23:19.643",
        "17:23:19.643",
        "17:23:19.667",
        "17:23:19.746",
        "17:23:19.747",
        "17:23:19.770",
        "17:23:19.860",
        "17:23:19.860",
        "17:23:19.985",
        "17:23:19.985",
        "17:23:20.108",
        "17:23:20.108",
        "17:23:31.365",
        "17:23:31.403",
        "17:23:31.440",
        "17:23:31.474",
        "17:23:31.509",
        "17:23:31.530",
        "17:23:31.533",
        "17:23:31.536",
        "17:23:31.539",
        "17:23:31.541",
        "17:23:31.545",
        "17:23:31.547",
        "17:23:31.550",
        "17:23:31.554",
        "17:23:31.558",
        "17:23:31.578",
        "17:23:31.609",
        "17:23:31.643",
        "17:23:31.680",
        "17:23:31.715"
      ]
    },
    {
      "pname": "Reachability",
      "endLocation": 6,
      "flowID": 3,
      "startLocation": 8,
      "lastSeen": 167,
      "largestGap": 156,
      "gapF": 156,
      "gapS": 0,
      "received_times": [
        "17:23:19.399",
        "17:23:19.399",
        "17:23:19.423",
        "17:23:19.520",
        "17:23:19.521",
        "17:23:19.545",
        "17:23:19.643",
        "17:23:19.643",
        "17:23:19.667",
        "17:23:19.746",
        "17:23:19.747",
        "17:23:19.770",
        "17:23:19.860",
        "17:23:19.860",
        "17:23:19.985",
        "17:23:19.985",
        "17:23:20.108",
        "17:23:20.108",
        "17:23:31.365",
        "17:23:31.403",
        "17:23:31.440",
        "17:23:31.474",
        "17:23:31.509",
        "17:23:31.530",
        "17:23:31.533",
        "17:23:31.536",
        "17:23:31.539",
        "17:23:31.541",
        "17:23:31.545",
        "17:23:31.547",
        "17:23:31.550",
        "17:23:31.554",
        "17:23:31.558",
        "17:23:31.578",
        "17:23:31.609",
        "17:23:31.643",
        "17:23:31.680",
        "17:23:31.715"
      ],
      "processing_times": [
        "17:23:19.399",
        "17:23:19.399",
        "17:23:19.423",
        "17:23:19.520",
        "17:23:19.521",
        "17:23:19.545",
        "17:23:19.643",
        "17:23:19.643",
        "17:23:19.667",
        "17:23:19.746",
        "17:23:19.747",
        "17:23:19.770",
        "17:23:19.860",
        "17:23:19.860",
        "17:23:19.985",
        "17:23:19.985",
        "17:23:20.108",
        "17:23:20.108",
        "17:23:31.365",
        "17:23:31.403",
        "17:23:31.440",
        "17:23:31.474",
        "17:23:31.509",
        "17:23:31.530",
        "17:23:31.533",
        "17:23:31.536",
        "17:23:31.539",
        "17:23:31.541",
        "17:23:31.545",
        "17:23:31.547",
        "17:23:31.550",
        "17:23:31.554",
        "17:23:31.558",
        "17:23:31.578",
        "17:23:31.609",
        "17:23:31.643",
        "17:23:31.680",
        "17:23:31.715"
      ]
    }
  ],
  "5": [
    {
      "pname": "Reachability",
      "endLocation": 5,
      "flowID": 1,
      "startLocation": 4,
      "lastSeen": 200,
      "largestGap": 189,
      "gapF": 189,
      "gapS": 0,
      "received_times": [
        "17:23:19.273",
        "17:23:19.401",
        "17:23:19.402",
        "17:23:19.419",
        "17:23:19.523",
        "17:23:19.523",
        "17:23:19.545",
        "17:23:19.645",
        "17:23:19.646",
        "17:23:19.666",
        "17:23:19.748",
        "17:23:19.749",
        "17:23:19.770",
        "17:23:19.882",
        "17:23:20.008",
        "17:23:20.130",
        "17:23:31.361",
        "17:23:31.400",
        "17:23:31.437",
        "17:23:31.471",
        "17:23:31.498",
        "17:23:31.501",
        "17:23:31.504",
        "17:23:31.507",
        "17:23:31.510",
        "17:23:31.512",
        "17:23:31.516",
        "17:23:31.519",
        "17:23:31.523",
        "17:23:31.526",
        "17:23:31.541",
        "17:23:31.575",
        "17:23:31.606",
        "17:23:31.640",
        "17:23:31.675",
        "17:23:31.712"
      ],
      "processing_times": [
        "17:23:19.273",
        "17:23:19.401",
        "17:23:19.402",
        "17:23:19.419",
        "17:23:19.523",
        "17:23:19.523",
        "17:23:19.545",
        "17:23:19.645",
        "17:23:19.646",
        "17:23:19.666",
        "17:23:19.748",
        "17:23:19.749",
        "17:23:19.770",
        "17:23:19.882",
        "17:23:20.008",
        "17:23:20.130",
        "17:23:31.361",
        "17:23:31.400",
        "17:23:31.437",
        "17:23:31.471",
        "17:23:31.498",
        "17:23:31.501",
        "17:23:31.504",
        "17:23:31.507",
        "17:23:31.510",
        "17:23:31.512",
        "17:23:31.516",
        "17:23:31.519",
        "17:23:31.523",
        "17:23:31.526",
        "17:23:31.541",
        "17:23:31.575",
        "17:23:31.606",
        "17:23:31.640",
        "17:23:31.675",
        "17:23:31.712"
      ]
    }
  ],
  "8": [
    {
      "pname": "Reachability",
      "endLocation": 8,
      "flowID": 2,
      "startLocation": 10,
      "lastSeen": 151,
      "largestGap": 140,
      "gapF": 140,
      "gapS": 0,
      "received_times": [
        "17:23:19.380",
        "17:23:19.400",
        "17:23:19.502",
        "17:23:19.521",
        "17:23:19.624",
        "17:23:19.645",
        "17:23:19.727",
        "17:23:19.748",
        "17:23:19.840",
        "17:23:19.966",
        "17:23:20.089",
        "17:23:31.373",
        "17:23:31.411",
        "17:23:31.446",
        "17:23:31.481",
        "17:23:31.515",
        "17:23:31.547",
        "17:23:31.580",
        "17:23:31.594",
        "17:23:31.598",
        "17:23:31.601",
        "17:23:31.604",
        "17:23:31.607",
        "17:23:31.610",
        "17:23:31.612",
        "17:23:31.615",
        "17:23:31.618",
        "17:23:31.621",
        "17:23:31.649",
        "17:23:31.684",
        "17:23:31.722"
      ],
      "processing_times": [
        "17:23:19.380",
        "17:23:19.400",
        "17:23:19.502",
        "17:23:19.521",
        "17:23:19.624",
        "17:23:19.645",
        "17:23:19.727",
        "17:23:19.748",
        "17:23:19.840",
        "17:23:19.966",
        "17:23:20.089",
        "17:23:31.373",
        "17:23:31.411",
        "17:23:31.446",
        "17:23:31.481",
        "17:23:31.515",
        "17:23:31.547",
        "17:23:31.580",
        "17:23:31.594",
        "17:23:31.598",
        "17:23:31.601",
        "17:23:31.604",
        "17:23:31.607",
        "17:23:31.610",
        "17:23:31.612",
        "17:23:31.615",
        "17:23:31.618",
        "17:23:31.621",
        "17:23:31.649",
        "17:23:31.684",
        "17:23:31.722"
      ]
    }
  ],
  "7": [
    {
      "pname": "Reachability",
      "endLocation": 7,
      "flowID": 1,
      "startLocation": 4,
      "lastSeen": 200,
      "largestGap": 189,
      "gapF": 189,
      "gapS": 0,
      "received_times": [
        "17:23:19.423",
        "17:23:19.545",
        "17:23:19.667",
        "17:23:19.770",
        "17:23:19.883",
        "17:23:20.008",
        "17:23:20.131",
        "17:23:31.407",
        "17:23:31.443",
        "17:23:31.477",
        "17:23:31.512",
        "17:23:31.544",
        "17:23:31.563",
        "17:23:31.566",
        "17:23:31.570",
        "17:23:31.573",
        "17:23:31.575",
        "17:23:31.579",
        "17:23:31.581",
        "17:23:31.584",
        "17:23:31.587",
        "17:23:31.590",
        "17:23:31.612",
        "17:23:31.646",
        "17:23:31.681",
        "17:23:31.718"
      ],
      "processing_times": [
        "17:23:19.423",
        "17:23:19.545",
        "17:23:19.667",
        "17:23:19.770",
        "17:23:19.883",
        "17:23:20.008",
        "17:23:20.131",
        "17:23:31.407",
        "17:23:31.443",
        "17:23:31.477",
        "17:23:31.512",
        "17:23:31.544",
        "17:23:31.563",
        "17:23:31.566",
        "17:23:31.570",
        "17:23:31.573",
        "17:23:31.575",
        "17:23:31.579",
        "17:23:31.581",
        "17:23:31.584",
        "17:23:31.587",
        "17:23:31.590",
        "17:23:31.612",
        "17:23:31.646",
        "17:23:31.681",
        "17:23:31.718"
      ]
    }
  ],
  "9": [
    {
      "pname": "Waypoint",
      "endLocation": 9,
      "flowID": 1,
      "startLocation": 4,
      "expectedWaypoints": [
        "s3"
      ],
      "unexpectedWaypoints": [],
      "errorFound": 1,
      "received_times": [
        "17:23:19.424",
        "17:23:19.544",
        "17:23:19.668",
        "17:23:19.770",
        "17:23:19.883",
        "17:23:20.009",
        "17:23:20.130"
      ],
      "processing_times": [
        "17:23:19.424",
        "17:23:19.544",
        "17:23:19.668",
        "17:23:19.770",
        "17:23:19.883",
        "17:23:20.009",
        "17:23:20.130"
      ]
    },
    {
      "pname": "Waypoint",
      "endLocation": 9,
      "flowID": 2,
      "startLocation": 5,
      "expectedWaypoints": [
        "s3"
      ],
      "unexpectedWaypoints": [],
      "errorFound": 1,
      "received_times": [
        "17:23:19.401",
        "17:23:19.523",
        "17:23:19.646",
        "17:23:19.749",
        "17:23:19.862",
        "17:23:19.987",
        "17:23:20.110"
      ],
      "processing_times": [
        "17:23:19.401",
        "17:23:19.523",
        "17:23:19.646",
        "17:23:19.749",
        "17:23:19.862",
        "17:23:19.987",
        "17:23:20.110"
      ]
    }
  ],
  "10": [
    {
      "pname": "Waypoint",
      "endLocation": 10,
      "flowID": 1,
      "startLocation": 1,
      "expectedWaypoints": [
        "s3"
      ],
      "unexpectedWaypoints": [],
      "errorFound": 1,
      "received_times": [
        "17:23:19.381",
        "17:23:19.503",
        "17:23:19.625",
        "17:23:19.728",
        "17:23:19.841",
        "17:23:19.967",
        "17:23:20.089"
      ],
      "processing_times": [
        "17:23:19.381",
        "17:23:19.503",
        "17:23:19.625",
        "17:23:19.728",
        "17:23:19.841",
        "17:23:19.967",
        "17:23:20.089"
      ]
    },
    {
      "pname": "Waypoint",
      "endLocation": 10,
      "flowID": 2,
      "startLocation": 4,
      "expectedWaypoints": [
        "s3"
      ],
      "unexpectedWaypoints": [],
      "errorFound": 1,
      "received_times": [
        "17:23:19.422",
        "17:23:19.544",
        "17:23:19.667",
        "17:23:19.769",
        "17:23:19.883",
        "17:23:20.008",
        "17:23:20.131"
      ],
      "processing_times": [
        "17:23:19.422",
        "17:23:19.544",
        "17:23:19.667",
        "17:23:19.769",
        "17:23:19.883",
        "17:23:20.008",
        "17:23:20.131"
      ]
    }
  ]
}