{
  "9": [
    {
      "pname": "Reachability",
      "endLocation": 9,
      "flowID": 1,
      "startLocation": 8,
      "lastSeen": 167,
      "largestGap": 156,
      "gapF": 156,
      "gapS": 0,
      "received_times": [
        "17:11:24.739",
        "17:11:24.860",
        "17:11:24.983",
        "17:11:25.086",
        "17:11:25.199",
        "17:11:25.325",
        "17:11:25.448",
        "17:11:36.728",
        "17:11:36.764",
        "17:11:36.799",
        "17:11:36.832",
        "17:11:36.863",
        "17:11:36.897",
        "17:11:36.930",
        "17:11:36.942",
        "17:11:36.946",
        "17:11:36.950",
        "17:11:36.954",
        "17:11:36.958",
        "17:11:36.961",
        "17:11:36.964",
        "17:11:36.967",
        "17:11:36.970",
        "17:11:36.973",
        "17:11:37.005",
        "17:11:37.042"
      ],
      "processing_times": [
        "17:11:24.739",
        "17:11:24.860",
        "17:11:24.983",
        "17:11:25.086",
        "17:11:25.199",
        "17:11:25.325",
        "17:11:25.448",
        "17:11:36.729",
        "17:11:36.764",
        "17:11:36.799",
        "17:11:36.832",
        "17:11:36.863",
        "17:11:36.897",
        "17:11:36.930",
        "17:11:36.942",
        "17:11:36.946",
        "17:11:36.950",
        "17:11:36.954",
        "17:11:36.958",
        "17:11:36.961",
        "17:11:36.964",
        "17:11:36.967",
        "17:11:36.970",
        "17:11:36.973",
        "17:11:37.005",
        "17:11:37.042"
      ]
    },
    {
      "pname": "Waypoint",
      "endLocation": 9,
      "flowID": 1,
      "startLocation": 8,
      "expectedWaypoints": [
        "s3"
      ],
      "unexpectedWaypoints": [],
      "errorFound": 1,
      "received_times": [
        "17:11:24.739",
        "17:11:24.860",
        "17:11:24.983",
        "17:11:25.086",
        "17:11:25.199",
        "17:11:25.325",
        "17:11:25.448"
      ],
      "processing_times": [
        "17:11:24.739",
        "17:11:24.860",
        "17:11:24.983",
        "17:11:25.086",
        "17:11:25.199",
        "17:11:25.325",
        "17:11:25.448"
      ]
    }
  ]
}